asgl/__init__.py
asgl/asgl.py
asgl/cv.py
asgl/skmodels.py
asgl/weights.py
asgl-2.1.3.dist-info/licenses/LICENSE
tests/__init__.py
tests/test_skmodels.py
asgl-2.1.3.dist-info/METADATA
asgl-2.1.3.dist-info/WHEEL
asgl-2.1.3.dist-info/top_level.txt
asgl-2.1.3.dist-info/RECORD
