Metadata-Version: 2.4
Name: asgl
Version: 2.1.3
Summary: A regression solver for high dimensional penalized linear, quantile and logistic regression models
Home-page: https://github.com/alvaromc317/asgl
Author: Alvaro Mendez Civieta
Author-email: alvaromc317@gmail.com
License: GNU General Public License
Keywords: variable-selection,regression,classification,penalization,lasso,adaptive-lasso,group-lasso,sparse-group-lasso,high-dimension,quantile-regression
Requires-Python: >=3.9
License-File: LICENSE
Requires-Dist: cvxpy>=1.2.0
Requires-Dist: numpy>=1.20.0
Requires-Dist: scikit-learn>=1.0
Requires-Dist: scipy>=1.1
Requires-Dist: pytest>=7.1.2
Dynamic: author
Dynamic: author-email
Dynamic: description
Dynamic: description-content-type
Dynamic: home-page
Dynamic: keywords
Dynamic: license
Dynamic: license-file
Dynamic: requires-dist
Dynamic: requires-python
Dynamic: summary
